iinput/__init__.py
iinput/iinput.py
iinput/utils.py
iinput-1.0.9.dist-info/LICENSE.txt
iinput-1.0.9.dist-info/METADATA
iinput-1.0.9.dist-info/WHEEL
iinput-1.0.9.dist-info/top_level.txt
iinput-1.0.9.dist-info/RECORD
